fpt_jax/__init__.py
fpt_jax/__version__.py
fpt_jax/_core.py
fpt_jax/py.typed
fpt_jax-0.1.1.dist-info/METADATA
fpt_jax-0.1.1.dist-info/WHEEL
fpt_jax-0.1.1.dist-info/licenses/LICENSE.md
fpt_jax-0.1.1.dist-info/RECORD
