Metadata-Version: 2.4
Name: fpt-jax
Version: 0.1.1
Summary: Fermat path tracing with JAX
Project-URL: Changelog, https://github.com/jeertmans/fpt-jax/releases
Project-URL: Documentation, https://github.com/jeertmans/fpt-jax
Project-URL: Founding, https://github.com/sponsors/jeertmans
Project-URL: Homepage, https://github.com/jeertmans/fpt-jax
Project-URL: Repository, https://github.com/jeertmans/fpt-jax
Author-email: Jérome Eertmans <jeertmans@icloud.com>
License-Expression: MIT
License-File: LICENSE.md
Keywords: differentiable,gpu,jax,propagation,radio,ray tracing
Classifier: License :: OSI Approved :: MIT License
Classifier: Operating System :: OS Independent
Classifier: Programming Language :: Python :: 3
Classifier: Programming Language :: Python :: 3.10
Classifier: Programming Language :: Python :: 3.11
Classifier: Programming Language :: Python :: 3.12
Classifier: Programming Language :: Python :: 3.13
Classifier: Programming Language :: Python :: 3.14
Classifier: Topic :: Scientific/Engineering
Requires-Python: >=3.10
Requires-Dist: jax>=0.5.3
